[
    {
        "name": "Valve"
    },
    {
        "name": "Hidden Path Entertainment"
    },
    {
        "name": "Haemimont Games"
    },
    {
        "name": "Irrational Games"
    },
    {
        "name": "Sony Online Entertainment"
    },
    {
        "name": "Relic Entertainment"
    },
    {
        "name": "DICE"
    },
    {
        "name": "Ubisoft"
    },
    {
        "name": "4A Games"
    },
    {
        "name": "Overkill Software"
    },
    {
        "name": "Infinity Ward"
    },
    {
        "name": "Bohemia Interactive"
    },
    {
        "name": "Crytek"
    },
    {
        "name": "MachineGames"
    },
    {
        "name": "Gearbox"
    },
    {
        "name": "GSC Game World"
    },
    {
        "name": "Techland"
    },
    {
        "name": "Bethesda Game Studios"
    },
    {
        "name": "Deck 13"
    },
    {
        "name": "EA Sports"
    },
    {
        "name": "EA LA"
    },
    {
        "name": "Hidden Path"
    },
    {
        "name": "Scott Cawthon"
    }
]
